newsbeuter_spread/__init__.py
newsbeuter_spread/app.py
newsbeuter_spread/db.py
newsbeuter_spread/item.py
newsbeuter_spread/static/core.js
newsbeuter_spread/static/spectre.min.css
newsbeuter_spread/templates/base.html
newsbeuter_spread/templates/index.html
tests/__init__.py
tests/test_newsbeuter_spread.py
newsbeuter_spread-1.2.2.dist-info/LICENSE
newsbeuter_spread-1.2.2.dist-info/METADATA
newsbeuter_spread-1.2.2.dist-info/WHEEL
newsbeuter_spread-1.2.2.dist-info/top_level.txt
newsbeuter_spread-1.2.2.dist-info/zip-safe
newsbeuter_spread-1.2.2.dist-info/RECORD
